nova6/__init__.py
nova6/helpers.py
nova6/importer.py
nova6/nova6.py
nova6/nova6dl.py
nova6/novaprinter.py
nova6/sgmllib3.py
nova6/socks.py
nova6-2.0.1.dist-info/DESCRIPTION.rst
nova6-2.0.1.dist-info/METADATA
nova6-2.0.1.dist-info/RECORD
nova6-2.0.1.dist-info/WHEEL
nova6-2.0.1.dist-info/entry_points.txt
nova6-2.0.1.dist-info/metadata.json
nova6-2.0.1.dist-info/top_level.txt
