Metadata-Version: 2.0
Name: nova6
Version: 2.0.1
Summary: A torrent search engine based on qBittorrent's
Home-page: https://github.com/Depaulicious/Nova6
Author: Davide Depau
Author-email: davide@depau.eu
License: GPLv2
Keywords: torrent search engine requests
Platform: UNKNOWN
Classifier: Development Status :: 4 - Beta
Classifier: Intended Audience :: Developers
Classifier: Topic :: Communications :: File Sharing
Classifier: Topic :: Internet :: WWW/HTTP :: Indexing/Search
Classifier: License :: OSI Approved :: GNU General Public License v2 (GPLv2)
Classifier: Programming Language :: Python :: 2
Classifier: Programming Language :: Python :: 2.7
Classifier: Programming Language :: Python :: 3
Classifier: Programming Language :: Python :: 3.3
Classifier: Programming Language :: Python :: 3.4
Classifier: Programming Language :: Python :: 3.5
Classifier: Programming Language :: Python :: 3.6
Requires-Dist: PySocks (!=1.5.7,>=1.5.6)
Requires-Dist: requests
Requires-Dist: requests[socks]
